aa_intel_tool/__init__.py
aa_intel_tool/admin.py
aa_intel_tool/app_settings.py
aa_intel_tool/apps.py
aa_intel_tool/auth_hooks.py
aa_intel_tool/constants.py
aa_intel_tool/exceptions.py
aa_intel_tool/form.py
aa_intel_tool/models.py
aa_intel_tool/providers.py
aa_intel_tool/tasks.py
aa_intel_tool/urls.py
aa_intel_tool/helper/data_structure.py
aa_intel_tool/helper/eve_character.py
aa_intel_tool/helper/urls.py
aa_intel_tool/locale/django.pot
aa_intel_tool/locale/cs_CZ/LC_MESSAGES/django.mo
aa_intel_tool/locale/cs_CZ/LC_MESSAGES/django.po
aa_intel_tool/locale/de/LC_MESSAGES/django.mo
aa_intel_tool/locale/de/LC_MESSAGES/django.po
aa_intel_tool/locale/es/LC_MESSAGES/django.mo
aa_intel_tool/locale/es/LC_MESSAGES/django.po
aa_intel_tool/locale/fr_FR/LC_MESSAGES/django.mo
aa_intel_tool/locale/fr_FR/LC_MESSAGES/django.po
aa_intel_tool/locale/it_IT/LC_MESSAGES/django.mo
aa_intel_tool/locale/it_IT/LC_MESSAGES/django.po
aa_intel_tool/locale/ja/LC_MESSAGES/django.mo
aa_intel_tool/locale/ja/LC_MESSAGES/django.po
aa_intel_tool/locale/ko_KR/LC_MESSAGES/django.mo
aa_intel_tool/locale/ko_KR/LC_MESSAGES/django.po
aa_intel_tool/locale/nl_NL/LC_MESSAGES/django.mo
aa_intel_tool/locale/nl_NL/LC_MESSAGES/django.po
aa_intel_tool/locale/pl_PL/LC_MESSAGES/django.mo
aa_intel_tool/locale/pl_PL/LC_MESSAGES/django.po
aa_intel_tool/locale/ru/LC_MESSAGES/django.mo
aa_intel_tool/locale/ru/LC_MESSAGES/django.po
aa_intel_tool/locale/sk/LC_MESSAGES/django.mo
aa_intel_tool/locale/sk/LC_MESSAGES/django.po
aa_intel_tool/locale/uk/LC_MESSAGES/django.mo
aa_intel_tool/locale/uk/LC_MESSAGES/django.po
aa_intel_tool/locale/zh_Hans/LC_MESSAGES/django.mo
aa_intel_tool/locale/zh_Hans/LC_MESSAGES/django.po
aa_intel_tool/management/commands/aa_intel_tool_load_eve_types.py
aa_intel_tool/migrations/0001_initial.py
aa_intel_tool/migrations/0002_alter_scan_raw_data.py
aa_intel_tool/migrations/__init__.py
aa_intel_tool/parser/__init__.py
aa_intel_tool/parser/general.py
aa_intel_tool/parser/helper/db.py
aa_intel_tool-2.12.1.dist-info/METADATA
aa_intel_tool-2.12.1.dist-info/WHEEL
aa_intel_tool-2.12.1.dist-info/licenses/LICENSE
aa_intel_tool-2.12.1.dist-info/RECORD
